sabs/__init__.py
sabs/__main__.py
sabs/scanpathtool.py
sabs-0.0.3.dist-info/LICENSE
sabs-0.0.3.dist-info/METADATA
sabs-0.0.3.dist-info/WHEEL
sabs-0.0.3.dist-info/top_level.txt
sabs-0.0.3.dist-info/RECORD
