Metadata-Version: 2.1
Name: sabs
Version: 0.0.3
Summary: SQUID Advanced Background Subtraction
Home-page: https://gitlab.com/ifw-dresden/sabs
Author: Börge Mehlhorn
Author-email: b.mehlhorn@ifw-dresden.de
Project-URL: Bug Tracker, https://gitlab.com/ifw-dresden/acfr/-/issues
Classifier: Programming Language :: Python :: 3
Classifier: License :: OSI Approved :: GNU Affero General Public License v3 or later (AGPLv3+)
Classifier: Operating System :: OS Independent
Requires-Python: >=3.9
License-File: LICENSE
